{
  "type": "FeatureCollection",
  "features": [
    {
      "type": "Feature",
      "properties": {},
      "geometry": {
        "type": "LineString",
        "coordinates": [
          [
            11.552145481109617,
            47.58248925963197
          ],
          [
            11.54611587524414,
            47.57756793579513
          ],
          [
            11.535816192626953,
            47.57571508225466
          ],
          [
            11.509037017822266,
            47.56471241397957
          ],
          [
            11.48946762084961,
            47.5610057315948
          ],
          [
            11.473331451416016,
            47.561584918005885
          ],
          [
            11.43402099609375,
            47.55903644990131
          ],
          [
            11.426639556884766,
            47.55370743418772
          ],
          [
            11.411876678466797,
            47.55150616084034
          ],
          [
            11.385612487792969,
            47.54733507355602
          ],
          [
            11.362953186035156,
            47.54362716173679
          ],
          [
            11.350421905517578,
            47.53933956173211
          ],
          [
            11.337375640869139,
            47.53806480221706
          ],
          [
            11.33188247680664,
            47.53169053973599
          ],
          [
            11.30767822265625,
            47.52995197003575
          ],
          [
            11.296123266220093,
            47.51838176976154
          ]
        ]
      }
    }
  ]
}