{
  "type": "FeatureCollection",
  "features": [
    {
      "type": "Feature",
      "properties": {},
      "geometry": {
        "type": "LineString",
        "coordinates": [
          [
            12.822943925857544,
            47.43955762671433
          ],
          [
            12.81829833984375,
            47.440860176947176
          ],
          [
            12.789459228515625,
            47.44074407350017
          ],
          [
            12.77486801147461,
            47.440627969796935
          ],
          [
            12.757701873779297,
            47.43877027569933
          ],
          [
            12.737789154052733,
            47.440627969796935
          ],
          [
            12.722167968749998,
            47.43935081215092
          ],
          [
            12.692738771438599,
            47.44490005450332
          ]
        ]
      }
    }
  ]
}