{
  "type": "FeatureCollection",
  "features": [
    {
      "type": "Feature",
      "properties": {},
      "geometry": {
        "type": "LineString",
        "coordinates": [
          [
            14.952049255371092,
            46.32126717642755
          ],
          [
            14.959945678710936,
            46.33555079758302
          ],
          [
            14.987411499023436,
            46.337447097476925
          ],
          [
            15.01487731933594,
            46.321326452271464
          ],
          [
            15.045776367187498,
            46.312552928782814
          ],
          [
            15.050239562988281,
            46.2954760942539
          ],
          [
            15.074615478515623,
            46.27032550490762
          ],
          [
            15.0897216796875,
            46.25940750573608
          ],
          [
            15.105171203613281,
            46.25299810220038
          ],
          [
            15.114784240722656,
            46.24183920528805
          ],
          [
            15.162506103515623,
            46.237564984022
          ],
          [
            15.200958251953125,
            46.234002878622505
          ],
          [
            15.233573913574219,
            46.23234048363967
          ],
          [
            15.246620178222654,
            46.23352791376573
          ],
          [
            15.265846252441404,
            46.226165432835074
          ],
          [
            15.26623249053955,
            46.22113284645877
          ]
        ]
      }
    }
  ]
}